plugin/__init__.py
plugin/version.py
astronomer_snowpatrol_plugin-0.0.1.dist-info/METADATA
astronomer_snowpatrol_plugin-0.0.1.dist-info/WHEEL
astronomer_snowpatrol_plugin-0.0.1.dist-info/entry_points.txt
astronomer_snowpatrol_plugin-0.0.1.dist-info/licenses/LICENSE.txt
astronomer_snowpatrol_plugin-0.0.1.dist-info/RECORD
