Metadata-Version: 2.3
Name: astronomer-snowpatrol-plugin
Version: 0.0.1
Summary: The SnowPatrol Plugin seamlessly integrates Airflow DAG and Task metadata with Snowflake using Query Tags
Project-URL: Homepage, https://github.com/astronomer/snowpatrol-plugin
Project-URL: Documentation, https://github.com/astronomer/snowpatrol-plugin#readme
Project-URL: Issues, https://github.com/astronomer/snowpatrol-plugin/issues
Project-URL: Source, https://github.com/astronomer/snowpatrol-plugin
Author-email: Olivier Daneau <olivier.daneau@astronomer.io>
License-Expression: Apache-2.0
License-File: LICENSE.txt
Keywords: Snowflake,airflow,apache-airflow,astronomer,dags
Classifier: Development Status :: 3 - Alpha
Classifier: Framework :: Apache Airflow
Classifier: Intended Audience :: Developers
Classifier: License :: OSI Approved :: Apache Software License
Classifier: Operating System :: OS Independent
Classifier: Programming Language :: Python
Classifier: Programming Language :: Python :: 3.8
Classifier: Programming Language :: Python :: 3.9
Classifier: Programming Language :: Python :: 3.10
Classifier: Programming Language :: Python :: 3.11
Classifier: Programming Language :: Python :: 3.12
Classifier: Programming Language :: Python :: Implementation :: PyPy
Requires-Python: >=3.8
Requires-Dist: apache-airflow>=2.3.0
